{
  "metadata": {
    "image_width": 4096,
    "image_height": 3000,
    "units_x": 4,
    "units_y": 6,
    "blocks_x": 2,
    "blocks_y": 1,
    "unit_space_x": 133,
    "unit_space_y": 136,
    "block_space_x": 252,
    "block_space_y": 0,
    "base_unit": {
      "x": 251,
      "y": 232,
      "w": 316,
      "h": 315
    }
  },
  "boxes": [
    {
      "index": 0,
      "x": 251,
      "y": 232,
      "w": 316,
      "h": 315
    },
    {
      "index": 1,
      "x": 700,
      "y": 232,
      "w": 316,
      "h": 315
    },
    {
      "index": 2,
      "x": 1149,
      "y": 232,
      "w": 316,
      "h": 315
    },
    {
      "index": 3,
      "x": 1598,
      "y": 232,
      "w": 316,
      "h": 315
    },
    {
      "index": 4,
      "x": 2166,
      "y": 232,
      "w": 316,
      "h": 315
    },
    {
      "index": 5,
      "x": 2615,
      "y": 232,
      "w": 316,
      "h": 315
    },
    {
      "index": 6,
      "x": 3064,
      "y": 232,
      "w": 316,
      "h": 315
    },
    {
      "index": 7,
      "x": 3513,
      "y": 232,
      "w": 316,
      "h": 315
    },
    {
      "index": 8,
      "x": 251,
      "y": 683,
      "w": 316,
      "h": 315
    },
    {
      "index": 9,
      "x": 700,
      "y": 683,
      "w": 316,
      "h": 315
    },
    {
      "index": 10,
      "x": 1149,
      "y": 683,
      "w": 316,
      "h": 315
    },
    {
      "index": 11,
      "x": 1598,
      "y": 683,
      "w": 316,
      "h": 315
    },
    {
      "index": 12,
      "x": 2166,
      "y": 683,
      "w": 316,
      "h": 315
    },
    {
      "index": 13,
      "x": 2615,
      "y": 683,
      "w": 316,
      "h": 315
    },
    {
      "index": 14,
      "x": 3064,
      "y": 683,
      "w": 316,
      "h": 315
    },
    {
      "index": 15,
      "x": 3513,
      "y": 683,
      "w": 316,
      "h": 315
    },
    {
      "index": 16,
      "x": 251,
      "y": 1134,
      "w": 316,
      "h": 315
    },
    {
      "index": 17,
      "x": 700,
      "y": 1134,
      "w": 316,
      "h": 315
    },
    {
      "index": 18,
      "x": 1149,
      "y": 1134,
      "w": 316,
      "h": 315
    },
    {
      "index": 19,
      "x": 1598,
      "y": 1134,
      "w": 316,
      "h": 315
    },
    {
      "index": 20,
      "x": 2166,
      "y": 1134,
      "w": 316,
      "h": 315
    },
    {
      "index": 21,
      "x": 2615,
      "y": 1134,
      "w": 316,
      "h": 315
    },
    {
      "index": 22,
      "x": 3064,
      "y": 1134,
      "w": 316,
      "h": 315
    },
    {
      "index": 23,
      "x": 3513,
      "y": 1134,
      "w": 316,
      "h": 315
    },
    {
      "index": 24,
      "x": 251,
      "y": 1585,
      "w": 316,
      "h": 315
    },
    {
      "index": 25,
      "x": 700,
      "y": 1585,
      "w": 316,
      "h": 315
    },
    {
      "index": 26,
      "x": 1149,
      "y": 1585,
      "w": 316,
      "h": 315
    },
    {
      "index": 27,
      "x": 1598,
      "y": 1585,
      "w": 316,
      "h": 315
    },
    {
      "index": 28,
      "x": 2166,
      "y": 1585,
      "w": 316,
      "h": 315
    },
    {
      "index": 29,
      "x": 2615,
      "y": 1585,
      "w": 316,
      "h": 315
    },
    {
      "index": 30,
      "x": 3064,
      "y": 1585,
      "w": 316,
      "h": 315
    },
    {
      "index": 31,
      "x": 3513,
      "y": 1585,
      "w": 316,
      "h": 315
    },
    {
      "index": 32,
      "x": 251,
      "y": 2036,
      "w": 316,
      "h": 315
    },
    {
      "index": 33,
      "x": 700,
      "y": 2036,
      "w": 316,
      "h": 315
    },
    {
      "index": 34,
      "x": 1149,
      "y": 2036,
      "w": 316,
      "h": 315
    },
    {
      "index": 35,
      "x": 1598,
      "y": 2036,
      "w": 316,
      "h": 315
    },
    {
      "index": 36,
      "x": 2166,
      "y": 2036,
      "w": 316,
      "h": 315
    },
    {
      "index": 37,
      "x": 2615,
      "y": 2036,
      "w": 316,
      "h": 315
    },
    {
      "index": 38,
      "x": 3064,
      "y": 2036,
      "w": 316,
      "h": 315
    },
    {
      "index": 39,
      "x": 3513,
      "y": 2036,
      "w": 316,
      "h": 315
    },
    {
      "index": 40,
      "x": 251,
      "y": 2487,
      "w": 316,
      "h": 315
    },
    {
      "index": 41,
      "x": 700,
      "y": 2487,
      "w": 316,
      "h": 315
    },
    {
      "index": 42,
      "x": 1149,
      "y": 2487,
      "w": 316,
      "h": 315
    },
    {
      "index": 43,
      "x": 1598,
      "y": 2487,
      "w": 316,
      "h": 315
    },
    {
      "index": 44,
      "x": 2166,
      "y": 2487,
      "w": 316,
      "h": 315
    },
    {
      "index": 45,
      "x": 2615,
      "y": 2487,
      "w": 316,
      "h": 315
    },
    {
      "index": 46,
      "x": 3064,
      "y": 2487,
      "w": 316,
      "h": 315
    },
    {
      "index": 47,
      "x": 3513,
      "y": 2487,
      "w": 316,
      "h": 315
    }
  ],
  "exclusions": []
}